main.py
apis/__init__.py
monitor/__init__.py
monitor/aio_docker_stats.py
monitor/aio_fps_monitor.py
monitor/aio_system_usage.py
monitor/aio_watch_screen.py
xtop/__init__.py
xtop/cli.py
xtop_cli-1.0.9.dist-info/licenses/LICENSE
xtop_cli-1.0.9.dist-info/METADATA
xtop_cli-1.0.9.dist-info/WHEEL
xtop_cli-1.0.9.dist-info/entry_points.txt
xtop_cli-1.0.9.dist-info/top_level.txt
xtop_cli-1.0.9.dist-info/RECORD
