Metadata-Version: 2.4
Name: xtop-cli
Version: 1.0.9
Summary: A lightweight monitor for FPS, System Usage and Docker Stats
Author-email: Qingliang Li <li.stayhere@gmail.com>
Requires-Python: >=3.8
License-File: LICENSE
Requires-Dist: orjson~=3.11.5
Requires-Dist: requests~=2.32.5
Requires-Dist: psutil~=7.1.3
Requires-Dist: plotext~=5.3.2
Requires-Dist: rich~=14.2.0
Requires-Dist: requests-unixsocket~=0.4.1
Requires-Dist: aiohttp~=3.13.2
Requires-Dist: docker~=7.1.0
Dynamic: license-file
